pflw-0.1.0.dist-info/METADATA
pflw-0.1.0.dist-info/WHEEL
pflw-0.1.0.dist-info/entry_points.txt
pflw/__init__.py
pflw/__init__.pyi
pflw/pflw.cpython-313-darwin.so
pflw/py.typed
pflw-0.1.0.dist-info/RECORD
