Metadata-Version: 2.4
Name: pflw
Version: 0.1.0
Classifier: Programming Language :: Rust
Classifier: Programming Language :: Python :: Implementation :: CPython
Classifier: Programming Language :: Python :: Implementation :: PyPy
Summary: Python DataFlow (pflw) - A Python library for data processing and transformation
Home-Page: https://github.com/Hennzau/pflw
Author: Enzo Le Van <dev@enzo-le-van.fr>
Author-email: Enzo Le Van <dev@enzo-le-van.fr>
License: Apache-2.0
Requires-Python: >=3.13
Project-URL: Source Code, https://github.com/Hennzau/pflw
